{
  "collection_id": "diverse_audio_creators",
  "title": "Diverse Audio Creators Collection",
  "description": "High-quality game audio from multiple creators beyond Kenney - orchestral, ambient, electronic, and professional SFX",
  "category": "audio",
  "minimum_plan": "pro",
  "creator_count": 25,
  "total_assets": 120,
  "style_variety": ["orchestral", "dark_ambient", "synthwave", "organic", "professional_sfx"],
  "differentiates_from": "kenney_style",
  "assets": [
    {
      "id": "epic_orchestral_001",
      "title": "Heroic Battle Theme",
      "creator": "OrchestraGames",
      "type": "audio",
      "category": "music", 
      "subcategory": "epic_orchestral",
      "duration": 180,
      "file_format": "ogg",
      "license": "CC0",
      "tags": ["epic", "battle", "orchestral", "heroic", "fantasy"],
      "game_genres": ["RPG", "fantasy", "adventure", "strategy"],
      "mood": ["heroic", "epic", "dramatic", "triumphant"],
      "file_url": "/assets/audio/epic_orchestral_001.ogg",
      "file_size": "2.1MB",
      "sample_rate": "44100Hz",
      "description": "Cinematic orchestral battle theme with full brass and percussion - perfect for epic RPG boss fights"
    },
    {
      "id": "dark_ambient_002", 
      "title": "Psychological Tension Drone",
      "creator": "HorrorSounds",
      "type": "audio",
      "category": "music",
      "subcategory": "dark_ambient", 
      "duration": 240,
      "file_format": "ogg",
      "license": "CC0",
      "tags": ["horror", "ambient", "dark", "psychological", "drone"],
      "game_genres": ["horror", "thriller", "psychological", "survival"],
      "mood": ["dark", "creepy", "tense", "atmospheric"],
      "file_url": "/assets/audio/dark_ambient_002.ogg", 
      "file_size": "1.8MB",
      "sample_rate": "44100Hz",
      "description": "Deep atmospheric drone with subtle dissonance - builds psychological tension without jump scares"
    },
    {
      "id": "synthwave_003",
      "title": "Neon City Drive",
      "creator": "CyberpunkBeats",
      "type": "audio", 
      "category": "music",
      "subcategory": "synthwave",
      "duration": 210,
      "file_format": "ogg", 
      "license": "CC0",
      "tags": ["synthwave", "cyberpunk", "electronic", "retro", "neon"],
      "game_genres": ["cyberpunk", "sci-fi", "racing", "action"],
      "mood": ["futuristic", "energetic", "neon", "cool"],
      "file_url": "/assets/audio/synthwave_003.ogg",
      "file_size": "2.3MB", 
      "sample_rate": "44100Hz",
      "description": "Retro-futuristic synthwave with driving bassline - captures that 80s cyberpunk aesthetic perfectly"
    },
    {
      "id": "realistic_sword_004",
      "title": "Professional Sword Combat Pack",
      "creator": "FoleySFX",
      "type": "audio",
      "category": "sfx", 
      "subcategory": "combat",
      "duration": 5,
      "file_format": "ogg",
      "license": "CC0", 
      "tags": ["sword", "combat", "realistic", "metal", "clang"],
      "game_genres": ["action", "RPG", "medieval", "realistic"],
      "mood": ["realistic", "impactful", "sharp"],
      "file_url": "/assets/audio/realistic_sword_004.ogg",
      "file_size": "180KB",
      "sample_rate": "44100Hz", 
      "description": "High-fidelity sword clash recorded with real medieval weapons - much more realistic than cartoon sounds"
    },
    {
      "id": "magical_spell_005",
      "title": "Arcane Spell Casting Collection", 
      "creator": "MagicAudio",
      "type": "audio",
      "category": "sfx",
      "subcategory": "magic",
      "duration": 3,
      "file_format": "ogg",
      "license": "CC0",
      "tags": ["magic", "spell", "mystical", "energy", "fantasy"],
      "game_genres": ["fantasy", "RPG", "magic", "wizard"],
      "mood": ["mystical", "powerful", "magical"],
      "file_url": "/assets/audio/magical_spell_005.ogg", 
      "file_size": "220KB",
      "sample_rate": "44100Hz",
      "description": "Layered magical energy sounds with ethereal tones - professional quality spell casting audio"
    }
  ],
  "collection_notes": {
    "why_not_kenney": "Kenney's audio is good but limited in style variety - this collection offers orchestral, horror, synthwave, and realistic audio that Kenney doesn't cover",
    "pro_tier_value": "Professional game soundtracks and SFX that would cost $50-200 individually",
    "creator_diversity": "25+ different audio artists vs single creator dependency",
    "style_coverage": "Covers game genres that need mature, realistic, or specialized audio"
  }
}